webkitscmpy/__init__.py
webkitscmpy/commit.py
webkitscmpy/commit_classifier.py
webkitscmpy/contributor.py
webkitscmpy/pull_request.py
webkitscmpy/scm_base.py
webkitscmpy/local/__init__.py
webkitscmpy/local/git.py
webkitscmpy/local/scm.py
webkitscmpy/local/svn.py
webkitscmpy/mocks/__init__.py
webkitscmpy/mocks/git-repo.json
webkitscmpy/mocks/svn-repo.json
webkitscmpy/mocks/local/__init__.py
webkitscmpy/mocks/local/git.py
webkitscmpy/mocks/local/svn.py
webkitscmpy/mocks/remote/__init__.py
webkitscmpy/mocks/remote/bitbucket.py
webkitscmpy/mocks/remote/git_hub.py
webkitscmpy/mocks/remote/svn.py
webkitscmpy/program/__init__.py
webkitscmpy/program/blame.py
webkitscmpy/program/branch.py
webkitscmpy/program/checkout.py
webkitscmpy/program/cherry_pick.py
webkitscmpy/program/classify.py
webkitscmpy/program/clean.py
webkitscmpy/program/clone.py
webkitscmpy/program/command.py
webkitscmpy/program/commit.py
webkitscmpy/program/conflict.py
webkitscmpy/program/credentials.py
webkitscmpy/program/find.py
webkitscmpy/program/install_git_lfs.py
webkitscmpy/program/install_hooks.py
webkitscmpy/program/land.py
webkitscmpy/program/log.py
webkitscmpy/program/pickable.py
webkitscmpy/program/publish.py
webkitscmpy/program/pull.py
webkitscmpy/program/pull_request.py
webkitscmpy/program/revert.py
webkitscmpy/program/review.py
webkitscmpy/program/setup.py
webkitscmpy/program/setup_git_svn.py
webkitscmpy/program/show.py
webkitscmpy/program/squash.py
webkitscmpy/program/trace.py
webkitscmpy/program/track.py
webkitscmpy/program/canonicalize/__init__.py
webkitscmpy/program/canonicalize/committer.py
webkitscmpy/program/canonicalize/message.py
webkitscmpy/remote/__init__.py
webkitscmpy/remote/bitbucket.py
webkitscmpy/remote/git_hub.py
webkitscmpy/remote/scm.py
webkitscmpy/remote/svn.py
webkitscmpy/test/__init__.py
webkitscmpy/test/branch_unittest.py
webkitscmpy/test/canonicalize_unittest.py
webkitscmpy/test/checkout_unittest.py
webkitscmpy/test/cherry_pick_unittest.py
webkitscmpy-7.0.0.dist-info/LICENSE
webkitscmpy-7.0.0.dist-info/METADATA
webkitscmpy-7.0.0.dist-info/WHEEL
webkitscmpy-7.0.0.dist-info/top_level.txt
webkitscmpy-7.0.0.dist-info/RECORD
