Metadata-Version: 2.1
Name: webkitscmpy
Version: 7.0.0
Summary: Library designed to interact with git and svn repositories.
Home-page: https://github.com/WebKit/WebKit/tree/main/Tools/Scripts/libraries/webkitscmpy
Author: Jonathan Bedard
Author-email: jbedard@apple.com
License: Modified BSD
Keywords: git svn
Classifier: Development Status :: 1 - Planning
Classifier: Intended Audience :: Developers
Classifier: License :: Other/Proprietary License
Classifier: Operating System :: MacOS
Classifier: Natural Language :: English
Classifier: Programming Language :: Python :: 3
Classifier: Topic :: Software Development :: Libraries :: Python Modules
License-File: LICENSE
Requires-Dist: fasteners
Requires-Dist: jinja2
Requires-Dist: monotonic
Requires-Dist: webkitcorepy
Requires-Dist: webkitbugspy
Requires-Dist: xmltodict
Requires-Dist: rapidfuzz
